<?xml version="1.0" encoding="UTF-8" standalone="yes" ?>
<eventposdef>
	<event name="VehicleCivilianSedan">
		<pos x="7534.94" y="248.288" z="470.087" a="-158.327"/>
		<pos x="6134.94" y="334.53" z="454.778" a="84.0607"/>
		<pos x="5600.25" y="350.589" z="500.996" a="-15.1777"/>
		<pos x="4285.5" y="411.812" z="562.486" a="-172.175"/>
		<pos x="3752.14" y="452.927" z="601.353" a="73.647"/>
		<pos x="2001.87" y="584.551" z="792.419" a="137.544"/>
		<pos x="1400.83" y="653.797" z="1767.05" a="-126.215"/>
		<pos x="796.341" y="870.725" z="3705.16" a="168.714"/>
		<pos x="1986.09" y="643.762" z="5763.18" a="-35.0184"/>
		<pos x="2591.28" y="213.909" z="7351.51" a="-12.6341"/>
		<pos x="2987.68" y="213.148" z="7760.1" a="55.0737"/>
		<pos x="4449.99" y="329.638" z="10085.6" a="-26.6994"/>
		<pos x="4482.38" y="362.881" z="10914.4" a="-169.151"/>
		<pos x="4170.03" y="405.3" z="11721.2" a="103.469"/>
		<pos x="10583.3" y="340.781" z="7171.08" a="129.681"/>
		<pos x="11233.2" y="497.656" z="4792.92" a="37.5154"/>
		<pos x="10173.3" y="384.979" z="4151" a="-41.2164"/>
		<pos x="9628.16" y="156.125" z="2422.07" a="65.0654"/>
		<pos x="7977.23" y="211.043" z="5348.87" a="127.054"/>
		<pos x="7433.38" y="226.523" z="5708.75" a="104.373"/>
	</event>
	<event name="VehicleSedan02">
		<pos x="5303.67" y="200.701" z="6711.1" a="77.5286"/>
		<pos x="4749.86" y="198.597" z="7469.86" a="90.7503"/>
		<pos x="3479.02" y="214.383" z="7430.47" a="-45.1936"/>
		<pos x="2456.21" y="214.457" z="7497.24" a="113.735"/>
		<pos x="6187.36" y="260.412" z="7119.17" a="85.5538"/>
		<pos x="4713.84" y="343.912" z="9387.88" a="50.0544"/>
		<pos x="1619.43" y="623.117" z="5241.83" a="59.4386"/>
		<pos x="5084.59" y="199.846" z="6080.17" a="-165.945"/>
		<pos x="1510.67" y="653.692" z="1622.71" a="93.0313"/>
		<pos x="6411.59" y="299.719" z="3258.81" a="144"/>
		<pos x="5725.31" y="198.607" z="5090.7" a="86.6148"/>
		<pos x="6373.44" y="217.302" z="5308.73" a="171"/>
		<pos x="11464.8" y="300.033" z="10285" a="77.0103"/>
		<pos x="10976.9" y="436.412" z="11405" a="-77.1019"/>
		<pos x="9572.01" y="265.626" z="5702.91" a="-13.9"/>
		<pos x="11212.6" y="441.914" z="5946.75" a="-127.627"/>
		<pos x="12067" y="351.353" z="6804.46" a="153"/>
		<pos x="2943.19" y="575.618" z="4218.75" a="-121.476"/>
		<pos x="334.288" y="396.684" z="7192.34" a="-145.633"/>
		<pos x="1626.22" y="214.583" z="10028.9" a="24.3232"/>
	</event>
	<event name="VehicleHatchback02">
		<pos x="7454.21" y="224.805" z="5791.68" a="-75.8476"/>
		<pos x="8112.81" y="198.978" z="4714.48" a="-159.103"/>
		<pos x="7689.51" y="198.769" z="4087.02" a="79.6362"/>
		<pos x="7772.55" y="165.881" z="2544.62" a="117.996"/>
		<pos x="8236.57" y="249.195" z="1248.89" a="-86.8624"/>
		<pos x="9398.54" y="142.265" z="1563.39" a="-150.86"/>
		<pos x="10683.7" y="236.327" z="2348.64" a="126"/>
		<pos x="10663.8" y="130.994" z="1009.65" a="13.7932"/>
		<pos x="7613.46" y="248.948" z="415.401" a="-2.08892"/>
		<pos x="8406.33" y="174.781" z="3086.58" a="14.4181"/>
		<pos x="6905.99" y="350.281" z="1836.65" a="-32.5847"/>
		<pos x="3834.66" y="568.282" z="4269.55" a="0"/>
		<pos x="4971.23" y="206.02" z="5342.41" a="26.3901"/>
		<pos x="1290.36" y="485.987" z="6520.78" a="27.9531"/>
		<pos x="1549.16" y="215.244" z="10370.6" a="-27.7572"/>
		<pos x="2244.86" y="412.575" z="10603.3" a="12.6888"/>
		<pos x="2238.2" y="400.442" z="12123.6" a="-135"/>
		<pos x="6811.81" y="285.812" z="11415.4" a="94.5572"/>
		<pos x="9635.59" y="230.243" z="10090.7" a="-56.369"/>
		<pos x="1759.53" y="215.294" z="8568.24" a="-174.625"/>
	</event>
    <event name="StaticHeliCrash">
		<zone smin="1" smax="3" dmin="3" dmax="5" r="45" />
		<pos x="5556.85" z="5195.19" a="0"/>
		<pos x="6578.72" z="5824.06" a="0"/>
		<pos x="8900.66" z="6241.09" a="0"/>
		<pos x="9486.69" z="7601.72" a="54"/>
		<pos x="9876.9" z="8432.25" a="0"/>
		<pos x="10056.6" z="9570.88" a="129.381"/>
		<pos x="9369.41" z="9974.05" a="0"/>
		<pos x="11039.7" z="11214.3" a="-9"/>
		<pos x="10815.7" z="11923.7" a="0"/>
		<pos x="9718.19" z="10637.5" a="0"/>
		<pos x="7667.26" z="5856.91" a="-36"/>
		<pos x="10753.2" z="8426.75" a="0"/>
		<pos x="9285.56" z="8751.81" a="-27"/>
		<pos x="10884.3" z="9275.13" a="-135"/>
		<pos x="10750.3" z="10405.6" a="-27"/>
		<pos x="966.607" z="3869.52" a="0"/>
		<pos x="926.745" z="6483.79" a="-36"/>
		<pos x="562.756" z="6794.83" a="-99"/>
		<pos x="1801.78" z="6560.89" a="-71.9999"/>
		<pos x="1681.48" z="5196.24" a="18"/>
		<pos x="4731.13" z="6438.14" a="0"/>
		<pos x="5805.02" z="6788.18" a="0"/>
		<pos x="6444.55" z="6472.91" a="-27"/>
		<pos x="4784.87" z="7159.79" a="0"/>
		<pos x="4859.57" z="7559.55" a="126"/>
		<pos x="4293.82" z="8226.53" a="0"/>
		<pos x="4166.38" z="9231.75" a="0"/>
		<pos x="5036.82" z="9766.09" a="-45"/>
		<pos x="4160.22" z="10189.5" a="-9"/>
		<pos x="4469.66" z="10865.7" a="-27"/>
		<pos x="4098.14" z="11733.8" a="-18"/>
		<pos x="4314.24" z="12012" a="-54"/>
		<pos x="6526.91" z="11614.7" a="-9"/>
		<pos x="8745.94" z="10970.1" a="-27"/>
		<pos x="7898.17" z="10846.8" a="0"/>
		<pos x="7177.71" z="9549.63" a="-162"/>
		<pos x="3129.46" z="10106.2" a="0"/>
		<pos x="2347.02" z="10691.2" a="-27"/>
		<pos x="2096.74" z="11783" a="-27"/>
		<pos x="2294.32" z="8763.41" a="-9"/>
		<pos x="3626.3" z="7029.8" a="0"/>
		<pos x="2698.57" z="7733.38" a="18"/>
		<pos x="2102.21" z="11056.8" a="0"/>
		<pos x="530.417" z="11672.2" a="0"/>
		<pos x="607.594" z="11145.3" a="0"/>
		<pos x="483.894" z="10314.7" a="0"/>
		<pos x="1240.39" z="10229.2" a="0"/>
		<pos x="1621.24" z="10041.5" a="-54"/>
		<pos x="3257.61" z="7583.52" a="-36"/>
		<pos x="675.521" z="8828.22" a="0"/>
		<pos x="1537.06" z="10426.9" a="-54"/>
		<pos x="12101.1" z="8951.87" a="-180"/>
		<pos x="887.196" z="7571.95" a="-18"/>
		<pos x="4858.41" z="8386.04" a="-27"/>
		<pos x="3086.68" z="11881.7" a="0"/>
		<pos x="5648.12" z="11705" a="36"/>
		<pos x="1752.49" z="8588.78" a="135"/>
		<pos x="1020.64" z="9656.34" a="18"/>
		<pos x="1334.71" z="11903.2" a="0"/>
		<pos x="2582.75" z="7376.48" a="-81"/>
	</event>
    <event name="StaticSantaCrash">
		<zone smin="1" smax="1" dmin="1" dmax="1" r="45" />
    </event>
	<event name="StaticChristmasTree">
	</event>
    <event name="StaticBonfire">
	</event>
    <event name="StaticContaminatedArea">
		<zone smin="0" smax="0" dmin="5" dmax="8" r="75" />
	</event>
    <event name="Loot" />
    <event name="VehicleOffroadHatchback">
		<pos x="1516.88" y="300.533" z="8044.09" a="-71.5881"/>
		<pos x="2995.14" y="213.689" z="7285.9" a="27"/>
		<pos x="3452.08" y="213.781" z="7746.08" a="-31.9356"/>
		<pos x="9900.59" y="221.015" z="7315.84" a="133.608"/>
		<pos x="7937.72" y="269.399" z="11868.2" a="-126"/>
		<pos x="7779.6" y="257.689" z="11418" a="57.7358"/>
		<pos x="2835.36" y="324.981" z="11494.6" a="135"/>
		<pos x="2121.89" y="458.243" z="10982.9" a="83.0271"/>
		<pos x="2299.56" y="213.675" z="7863.14" a="-88.3121"/>
		<pos x="4172.76" y="405.311" z="11956.2" a="115.772"/>
		<pos x="7698.68" y="203.477" z="4523.77" a="0.0241623"/>
		<pos x="6391.69" y="212.803" z="5035.56" a="-16.1826"/>
		<pos x="6218.08" y="202.05" z="4437.09" a="-78.4145"/>
		<pos x="6398.72" y="201.36" z="3670.8" a="7.51777"/>
		<pos x="863.099" y="697.475" z="2501.14" a="141.044"/>
		<pos x="3046.49" y="600.71" z="5621.58" a="10.5581"/>
		<pos x="11320.9" y="481.042" z="3925.02" a="158.921"/>
		<pos x="9676.21" y="272.249" z="6150.97" a="-180"/>
		<pos x="3918.35" y="306.25" z="10170.4" a="91.195"/>
		<pos x="4793.61" y="451.716" z="11790.6" a="153"/>
    </event>
	<event name="VehicleOffroad02">
		<pos x="4869.41" y="197.437" z="8062.35" a="65.5244"/>
		<pos x="1019.69" y="867.895" z="4047.67" a="-105.642"/>
		<pos x="8742.72" y="165.764" z="2770.59" a="20.9465"/>
		<pos x="12042.3" y="611.369" z="8817.04" a="-97.0006"/>
		<pos x="10735" y="436.669" z="11263.2" a="-65.7858"/>
		<pos x="9568.2" y="227.758" z="9120.35" a="134.262"/>
		<pos x="9725.88" y="227.486" z="8963.44" a="-77.9437"/>
		<pos x="5645.81" y="590.988" z="11729.8" a="178.098"/>
		<pos x="1458.24" y="214.338" z="10499.1" a="62.9253"/>
		<pos x="2681.4" y="214.106" z="7475.97" a="-146.837"/>
    </event>
    <event name="StaticPoliceCar">
		<zone smin="1" smax="3" dmin="3" dmax="5" r="45" />
    </event>
	<event name="ItemPlanks">
		<pos x="10509.3" y="133.527" z="1192.8" a="45"/>
		<pos x="9732.76" y="151.088" z="2107.22" a="45"/>
		<pos x="11285.3" y="480.801" z="3901.24" a="-36"/>
		<pos x="8114.32" y="197.954" z="4990.42" a="-90"/>
		<pos x="8132.85" y="197.954" z="4828.71" a="0"/>
		<pos x="7704.85" y="202.747" z="4569.22" a="45"/>
		<pos x="6309.98" y="205.298" z="4492.13" a="-36"/>
		<pos x="5885.14" y="204.628" z="4987.17" a="-9"/>
		<pos x="5551.53" y="204.469" z="5777.08" a="90"/>
		<pos x="5584.47" y="204.469" z="5733.61" a="135"/>
		<pos x="1730.37" y="213.611" z="8645.42" a="-27"/>
		<pos x="1629.72" y="653.269" z="1763.83" a="-27"/>
		<pos x="1890.51" y="584.6" z="1104.99" a="-18"/>
		<pos x="841.804" y="648.167" z="4839.38" a="-117"/>
		<pos x="2857.59" y="593.95" z="5681.87" a="-27"/>
		<pos x="2934.93" y="596.183" z="5642.39" a="0"/>
		<pos x="584.007" y="429.407" z="6869.32" a="-90"/>
		<pos x="639.374" y="532.365" z="8928.32" a="-45"/>
		<pos x="1517.96" y="214.017" z="10419.3" a="-27"/>
		<pos x="2127.24" y="456.915" z="10937.4" a="117"/>
		<pos x="2908.26" y="322.909" z="11325.1" a="-54"/>
		<pos x="4108.44" y="404.975" z="11952.5" a="-90"/>
		<pos x="4054.02" y="404.969" z="11785" a="-90"/>
		<pos x="4233.43" y="404.986" z="11953.1" a="-90"/>
		<pos x="4499.42" y="365.865" z="10996.3" a="-54"/>
		<pos x="7833.76" y="256.89" z="11389.6" a="-99"/>
		<pos x="7943.47" y="252.753" z="11561.7" a="-81"/>
		<pos x="7882.82" y="269.248" z="11907.8" a="27"/>
		<pos x="7851.09" y="269.152" z="11884.5" a="-18"/>
		<pos x="8265.24" y="263.967" z="11690.1" a="9"/>
		<pos x="9656.36" y="229.215" z="10082.9" a="45"/>
		<pos x="11359.1" y="279.637" z="10128.7" a="-36"/>
		<pos x="10430.4" y="256.576" z="9741.82" a="0"/>
		<pos x="10241.3" y="230.32" z="8499.98" a="-90"/>
		<pos x="9722.56" y="220.342" z="7104.51" a="-45"/>
		<pos x="11236.1" y="441.958" z="5928.56" a="-18"/>
		<pos x="6360.33" y="298.755" z="3133.34" a="-45"/>
		<pos x="8392.75" y="247.972" z="1359.8" a="45"/>
		<pos x="3418.01" y="213.177" z="7169" a="0"/>
		<pos x="3291.03" y="202.826" z="7776.51" a="-18"/>
		<pos x="2732.28" y="213.177" z="7457.92" a="0"/>
		<pos x="2314.26" y="255.53" z="7133.12" a="0"/>
		<pos x="4701.48" y="341.896" z="9429.37" a="45"/>
		<pos x="6414.34" y="1166.81" z="8955.82" a="0"/>
		<pos x="6055.86" y="655.543" z="10356.1" a="0"/>
		<pos x="4765.96" y="330.838" z="10560.4" a="-63"/>
		<pos x="10772.1" y="435.885" z="11390.7" a="18"/>
		<pos x="10845.7" y="332.477" z="3006.2" a="45"/>
		<pos x="11463.3" y="480.948" z="3810.32" a="81"/>
		<pos x="7827.3" y="196.038" z="4097.27" a="-27"/>
		<pos x="7190.98" y="193.344" z="4030.11" a="0"/>
		<pos x="4954.59" y="204.609" z="5253.75" a="27"/>
		<pos x="4091.16" y="237.785" z="5622.49" a="-72"/>
		<pos x="1497.45" y="758.382" z="4459.91" a="-63"/>
		<pos x="1952.4" y="643.382" z="5771.51" a="-54"/>
		<pos x="2004.48" y="643.382" z="5750.61" a="-45"/>
		<pos x="1657.07" y="214.22" z="10063.8" a="-99"/>
		<pos x="4143.19" y="306.288" z="10177.5" a="-54"/>
		<pos x="4186.41" y="371.264" z="11161" a="63"/>
		<pos x="6352.81" y="234.247" z="6674.56" a="-81"/>
    </event>
    <event name="VehicleTruck01">
		<pos x="4069.27" y="406.26" z="11945" a="173.374"/>
		<pos x="2840.21" y="212.961" z="7651.15" a="71.2928"/>
		<pos x="6195.26" y="205.839" z="4629.33" a="-151.83"/>
		<pos x="8132.97" y="198.981" z="4939.37" a="-140.059"/>
		<pos x="8484.73" y="204.292" z="5692.76" a="177.699"/>
		<pos x="11229.7" y="477.023" z="8021.65" a="171.951"/>
		<pos x="8122.42" y="266.867" z="11729" a="-0.00495954"/>
		<pos x="4490.41" y="367.227" z="10983" a="-23.5212"/>
		<pos x="4928.23" y="198.587" z="8170.04" a="-101.141"/>
	</event>
	<event name="StaticTrain">
		<zone smin="0" smax="0" dmin="1" dmax="2" r="20" />
	</event>
	<event name="StaticMilitaryConvoy">
	</event>
	<event name="StaticPoliceSituation">
		<zone smin="0" smax="0" dmin="1" dmax="2" r="20" />
	</event>
	
	<!--Bitterroot Event-->
	<event name="StaticCultCrash">
	<zone smin="1" smax="3" dmin="3" dmax="5" r="45" />
		<pos x="7872.95" z="11952.3" a="90"/>
		<pos x="4817.64" z="11022.6" a="81"/>
		<pos x="2963.18" z="11198.8" a="98.9999"/>
		<pos x="3632.49" z="8305.19" a="144"/>
		<pos x="2135.65" z="7179.79" a="162"/>
		<pos x="4661.8" z="5048" a="126"/>
		<pos x="4101.31" z="5999.71" a="-36"/>
		<pos x="6132.16" z="5707.94" a="0"/>
		<pos x="10018.4" z="7826.78" a="135"/>
		<pos x="2913.48" z="5907.01" a="-27"/>
    </event>
	
	<!--GolfCart mod-->
	<event name="VehicleGolfCart">
		<pos x="6357.99" y="234.672" z="6644.47" a="99"/>
		<pos x="6444.66" y="227.436" z="6150.3" a="-90"/>
		<pos x="6623.16" y="233.036" z="6123.47" a="0"/>
		<pos x="6306.62" y="231.564" z="6364.92" a="-147.599"/>
		<pos x="6490.01" y="230.423" z="6215.45" a="110.627"/>
		<pos x="6275.96" y="235.417" z="6577.37" a="45"/>
		<pos x="6277.51" y="231.796" z="6215.38" a="-27"/>
		<pos x="6486.66" y="230.423" z="6214.6" a="110.949"/>
		<pos x="6576.95" y="233.059" z="6377.98" a="180"/>
		<pos x="6446.03" y="234.89" z="6437.23" a="-30.9667"/>
	</event>

    <event name="VehicleTransitBus" />
    <event name="InfectedVillage" />
    <event name="InfectedSolitude" />
    <event name="InfectedArmy" />
    <event name="InfectedCity" />
    <event name="InfectedMedic" />
    <event name="InfectedPolice" />
    <event name="InfectedFirefighter" />
    <event name="InfectedPrisoner" />
    <event name="AnimalDeer" />
    <event name="AnimalCow" />
    <event name="AnimalSheep" />
    <event name="AnimalRoeDeer" />
    <event name="AnimalWolf" />
    <event name="AnimalWildBoar" />
	<!--Bitterroot Custom Items-->
	<event name="AnimalBearBlack" />
	<event name="MF_Moose" />
	<event name="MF_MountainLion" />
</eventposdef>
